[
 {
  "nr": 1,
  "scoritoId": 2799,
  "start": "2026-07-04T17:05:00",
  "van": "Barcelona",
  "naar": "Barcelona",
  "km": 19,
  "terrain": "vlak",
  "type": "TTT",
  "profielUrl": "https://cdn.scorito-sports.com/cycling/stage/images/2799_Compressed_37dfdc58-e857-46c0-a41e-0798a8d1f8fa.png",
  "beschrijving": "De Tour opent voor het eerst sinds 2019 met een ploegentijdrit, dwars door het hart van Barcelona. Bijzonder dit jaar: de tijd van de snelste renner telt als ploegtijd, en de winnaar pakt direct de gele trui."
 },
 {
  "nr": 2,
  "scoritoId": 2800,
  "start": "2026-07-05T13:55:00",
  "van": "Tarragone",
  "naar": "Barcelona",
  "km": 182,
  "terrain": "heuvel",
  "type": "rit",
  "profielUrl": "https://cdn.scorito-sports.com/cycling/stage/images/2800_Compressed_9109c9c6-2ea6-440c-ba4d-b9709481639f.png",
  "beschrijving": "Heuvelrit langs de Catalaanse kust terug naar Barcelona. Punchers en aanvallers krijgen hun kans; de lastige finale kan het peloton breken."
 },
 {
  "nr": 3,
  "scoritoId": 2801,
  "start": "2026-07-06T12:20:00",
  "van": "Granollers",
  "naar": "Les Angles",
  "km": 196,
  "terrain": "heuvel",
  "type": "rit",
  "profielUrl": "https://cdn.scorito-sports.com/cycling/stage/images/2801_Compressed_df6b36e6-3b18-4c38-8e9f-de6ba84b2720.png",
  "beschrijving": "Lange rit de Pyreneeën in met aankomst bergop in skioord Les Angles. De eerste echte krachtmeting tussen de klassementsrenners."
 },
 {
  "nr": 4,
  "scoritoId": 2802,
  "start": "2026-07-07T13:25:00",
  "van": "Carcassonne",
  "naar": "Foix",
  "km": 182,
  "terrain": "heuvel",
  "type": "rit",
  "profielUrl": "https://cdn.scorito-sports.com/cycling/stage/images/2802_Compressed_39f9140e-c392-4d9b-8ebd-3dd2047932ed.png",
  "beschrijving": "Heuvelachtige rit door de Ariège naar Foix — klassiek terrein voor de vroege vlucht en aanvallers."
 },
 {
  "nr": 5,
  "scoritoId": 2803,
  "start": "2026-07-08T14:15:00",
  "van": "Lannemezan",
  "naar": "Pau",
  "km": 158,
  "terrain": "vlak",
  "type": "rit",
  "profielUrl": "https://cdn.scorito-sports.com/cycling/stage/images/2803_Compressed_7af2407b-a351-415d-a6e2-81f00e6ce8e8.png",
  "beschrijving": "Overgangsrit naar wielerstad Pau. Waarschijnlijk een dag voor de sprinters, al loert een sterke vluchtgroep."
 },
 {
  "nr": 6,
  "scoritoId": 2804,
  "start": "2026-07-09T12:40:00",
  "van": "Pau",
  "naar": "Gavarnie-Gèdre",
  "km": 186,
  "terrain": "berg",
  "type": "rit",
  "profielUrl": "https://cdn.scorito-sports.com/cycling/stage/images/2804_Compressed_0041ebba-2829-4e0d-b9e3-05f27b9c4093.png",
  "beschrijving": "Zware Pyreneeënrit richting de wereldberoemde cirque van Gavarnie. Hier vallen de eerste grote gaten in het klassement."
 },
 {
  "nr": 7,
  "scoritoId": 2805,
  "start": "2026-07-10T13:25:00",
  "van": "Hagetmau",
  "naar": "Bordeaux",
  "km": 175,
  "terrain": "vlak",
  "type": "rit",
  "profielUrl": "https://cdn.scorito-sports.com/cycling/stage/images/2805_Compressed_0203e4cb-b3a9-450c-80d2-c854a7f0d7e7.png",
  "beschrijving": "Vlakke rit door de Landes naar Bordeaux — een klassieke sprintkans."
 },
 {
  "nr": 8,
  "scoritoId": 2806,
  "start": "2026-07-11T13:25:00",
  "van": "Périgueux",
  "naar": "Bergerac",
  "km": 182,
  "terrain": "vlak",
  "type": "rit",
  "profielUrl": "https://cdn.scorito-sports.com/cycling/stage/images/2806_Compressed_44e8c7f5-57ff-4a57-8a63-241dbbd7ed08.png",
  "beschrijving": "Rustige dag door de Dordogne. De sprintersploegen houden de touwtjes strak richting Bergerac."
 },
 {
  "nr": 9,
  "scoritoId": 2807,
  "start": "2026-07-12T13:45:00",
  "van": "Malemort",
  "naar": "Ussel",
  "km": 185,
  "terrain": "heuvel",
  "type": "rit",
  "profielUrl": "https://cdn.scorito-sports.com/cycling/stage/images/2807_Compressed_e028f6a7-34e8-47b4-ab40-15cfe381f8a3.png",
  "beschrijving": "Golvende rit door de Corrèze, zonder grote cols maar ook zonder rust — ideaal terrein voor de vroege vlucht."
 },
 {
  "nr": 10,
  "scoritoId": 2808,
  "start": "2026-07-14T13:25:00",
  "van": "Aurillac",
  "naar": "Le Lioran",
  "km": 167,
  "terrain": "berg",
  "type": "rit",
  "profielUrl": "https://cdn.scorito-sports.com/cycling/stage/images/2808_Compressed_7c620e15-9e86-46d5-8220-e33e7e57978a.png",
  "beschrijving": "Bergrit door het Centraal Massief met aankomst bij Le Lioran. De hellingen zijn er kort maar venijnig — quatorze juillet, dus de Fransen willen winnen."
 },
 {
  "nr": 11,
  "scoritoId": 2809,
  "start": "2026-07-15T14:05:00",
  "van": "Vichy",
  "naar": "Nevers",
  "km": 161,
  "terrain": "vlak",
  "type": "rit",
  "profielUrl": "https://cdn.scorito-sports.com/cycling/stage/images/2809_Compressed_b828132d-3288-45cc-90df-3da1b6f5ac3c.png",
  "beschrijving": "Vlakke overgangsrit. De sprinters willen scoren nu het nog kan."
 },
 {
  "nr": 12,
  "scoritoId": 2810,
  "start": "2026-07-16T13:40:00",
  "van": "Nevers Magny-Cours",
  "naar": "Chalon-sur-Saône",
  "km": 181,
  "terrain": "vlak",
  "type": "rit",
  "profielUrl": "https://cdn.scorito-sports.com/cycling/stage/images/2810_Compressed_8bda9e2c-f0f4-4c02-9dbc-8ec1484583be.png",
  "beschrijving": "Start op het racecircuit van Magny-Cours, finish in Chalon-sur-Saône. Opnieuw een dag voor de rappe mannen."
 },
 {
  "nr": 13,
  "scoritoId": 2811,
  "start": "2026-07-17T13:20:00",
  "van": "Dole",
  "naar": "Belfort",
  "km": 205,
  "terrain": "heuvel",
  "type": "rit",
  "profielUrl": "https://cdn.scorito-sports.com/cycling/stage/images/2811_Compressed_67adca43-7e1a-46c7-b8d7-c4ba4fc06328.png",
  "beschrijving": "Met 205 kilometer de langste rit van deze Tour, door de Jura richting Belfort. Lastig heuvelwerk waar een sterke groep ver kan komen."
 },
 {
  "nr": 14,
  "scoritoId": 2812,
  "start": "2026-07-18T13:30:00",
  "van": "Mulhouse",
  "naar": "Le Markstein Fellering",
  "km": 155,
  "terrain": "berg",
  "type": "rit",
  "profielUrl": "https://cdn.scorito-sports.com/cycling/stage/images/2812_Compressed_30220258-94e7-479f-8fea-75f83143c7bc.png",
  "beschrijving": "Bergrit door de Vogezen met finish op Le Markstein. Opeenvolgende beklimmingen nodigen uit tot aanvallen van ver."
 },
 {
  "nr": 15,
  "scoritoId": 2813,
  "start": "2026-07-19T13:20:00",
  "van": "Champagnole",
  "naar": "Plateau de Solaison",
  "km": 184,
  "terrain": "berg",
  "type": "rit",
  "profielUrl": "https://cdn.scorito-sports.com/cycling/stage/images/2813_Compressed_8018bc11-ab4d-41a3-ab27-32984d54a180.png",
  "beschrijving": "Zware dag met aankomst bergop op het Plateau de Solaison: een lange, steile slotklim die grote verschillen kan maken."
 },
 {
  "nr": 16,
  "scoritoId": 2814,
  "start": "2026-07-21T13:00:00",
  "van": "Évian-les-Bains",
  "naar": "Thonon-les-Bains",
  "km": 26,
  "terrain": "heuvel",
  "type": "ITT",
  "profielUrl": "https://cdn.scorito-sports.com/cycling/stage/images/2814_Compressed_07c06c32-ebd3-4f17-812d-18c1db564db2.png",
  "beschrijving": "Individuele tijdrit van 26 kilometer langs het Meer van Genève. De specialisten kunnen hier veel tijd pakken in het klassement."
 },
 {
  "nr": 17,
  "scoritoId": 2815,
  "start": "2026-07-22T13:35:00",
  "van": "Chambery",
  "naar": "Voiron",
  "km": 175,
  "terrain": "vlak",
  "type": "rit",
  "profielUrl": "https://cdn.scorito-sports.com/cycling/stage/images/2815_Compressed_4063077e-0ebf-421a-b3a5-d783ac2e2170.png",
  "beschrijving": "Adempauze tussen de Alpenritten. Kans voor de sprinters — of voor een vlucht die de bergdagen wil ontlopen."
 },
 {
  "nr": 18,
  "scoritoId": 2816,
  "start": "2026-07-23T12:50:00",
  "van": "Voiron",
  "naar": "Orcières-Merlette",
  "km": 185,
  "terrain": "berg",
  "type": "rit",
  "profielUrl": "https://cdn.scorito-sports.com/cycling/stage/images/2816_Compressed_f2bbfc8a-7c65-4452-9170-9b10f62faf25.png",
  "beschrijving": "Alpenrit met finish in Orcières-Merlette, waar de slotklim hard en gestaag omhoog loopt."
 },
 {
  "nr": 19,
  "scoritoId": 2817,
  "start": "2026-07-24T14:15:00",
  "van": "Gap",
  "naar": "Alpe d'Huez",
  "km": 128,
  "terrain": "berg",
  "type": "rit",
  "profielUrl": "https://cdn.scorito-sports.com/cycling/stage/images/2817_Compressed_9b84e4b9-829f-45f0-b76e-0df782e30ae3.png",
  "beschrijving": "Korte, explosieve bergrit met finish op de mythische Alpe d'Huez en zijn 21 haarspeldbochten."
 },
 {
  "nr": 20,
  "scoritoId": 2818,
  "start": "2026-07-25T11:30:00",
  "van": "Le Bourg d'Oisans",
  "naar": "Alpe d'Huez",
  "km": 171,
  "terrain": "berg",
  "type": "rit",
  "profielUrl": "https://cdn.scorito-sports.com/cycling/stage/images/2818_Compressed_0c0a2502-7d2a-4bc2-ae96-aed6ba5ec0b1.png",
  "beschrijving": "Uniek: twee dagen op rij finishen op Alpe d'Huez, nu na een langere aanloop door de Alpen. De laatste kans voor de klimmers om het klassement op te schudden."
 },
 {
  "nr": 21,
  "scoritoId": 2819,
  "start": "2026-07-26T16:25:00",
  "van": "Thoiry",
  "naar": "Paris Champs-Élysées",
  "km": 130,
  "terrain": "heuvel",
  "type": "rit",
  "profielUrl": "https://cdn.scorito-sports.com/cycling/stage/images/2819_Compressed_103dcf4c-ebb2-49c7-acc3-a488165ede72.png",
  "beschrijving": "De slotrit eindigt traditiegetrouw op de Champs-Élysées: eerst het defilé met champagne, dan de meest prestigieuze massasprint van het jaar."
 }
]